wjwgym/__init__.py
wjwgym/__version__.py
wjwgym/agents/DDPG_base.py
wjwgym/agents/DQN_base.py
wjwgym/agents/Linear_base.py
wjwgym/agents/Utils.py
wjwgym/agents/__init__.py
wjwgym/envs/__init__.py
wjwgym/envs/findtreasure_env.py
wjwgym/envs/maze_env.py
wjwgym/models/__init__.py
wjwgym/models/actor_net.py
wjwgym/models/critic_net.py
wjwgym/models/dqn_net.py
wjwgym-0.1.2.dist-info/LICENCE
wjwgym-0.1.2.dist-info/METADATA
wjwgym-0.1.2.dist-info/WHEEL
wjwgym-0.1.2.dist-info/top_level.txt
wjwgym-0.1.2.dist-info/RECORD
