Metadata-Version: 2.1
Name: wjwgym
Version: 0.1.2
Summary: Reinforcement Learning Tools
Home-page: https://github.com/LampV/Reinforcement-Learning
Author: ('Jiawei Wu',)
Author-email: 13260322877@163.com
License: MIT
Platform: UNKNOWN
Classifier: License :: OSI Approved :: MIT License
Classifier: Programming Language :: Python
Classifier: Programming Language :: Python :: 3
Classifier: Programming Language :: Python :: 3.6
Classifier: Programming Language :: Python :: Implementation :: PyPy
Requires-Python: >=3.6.0
Requires-Dist: numpy
Requires-Dist: gym
Requires-Dist: torch
Requires-Dist: pandas
